bson_extra/__init__.py
bson_extra/__version__.py
bson_extra/tests/__init__.py
bson_extra/tests/test_bson_extra.py
bson_extra-0.0.4.dist-info/METADATA
bson_extra-0.0.4.dist-info/WHEEL
bson_extra-0.0.4.dist-info/top_level.txt
bson_extra-0.0.4.dist-info/RECORD
