Metadata-Version: 2.1
Name: bson-extra
Version: 0.0.4
Summary: Provides hooks for supplying extra type handling for bson objects. Primarily to give full timezone support for bson.dumps and bson.loads
Home-page: UNKNOWN
Author: AgileTek Engineering
License: UNKNOWN
Platform: UNKNOWN
Classifier: License :: OSI Approved :: GNU Affero General Public License v3
Classifier: Programming Language :: Python :: 3.6
Classifier: Natural Language :: English
Classifier: Operating System :: OS Independent
Requires-Dist: pymongo (==3.12.2)
Requires-Dist: pytz
Provides-Extra: pre-commit
Requires-Dist: pre-commit ; extra == 'pre-commit'
